[{"url":"https://i.pinimg.com/originals/90/9e/7c/909e7c7558a9c6935668ee2c8e5dcf2d.jpg","type":"image","desc":"red and black stars on a white background","cat":"lofi"},{"url":"https://i.pinimg.com/originals/1d/78/b1/1d78b1daf18b2551436af488d8bdd922.jpg","type":"image","desc":"the stars are all different colors and sizes on this black background, but there is no image to describe","cat":"lofi"},{"url":"https://i.pinimg.com/originals/22/fc/f5/22fcf5f9445fa1b76f84d19757ac07b3.jpg","type":"image","desc":"the silhouette of a mountain against an orange sky","cat":"lofi"},{"url":"https://i.pinimg.com/originals/f6/be/a4/f6bea4edaa5042aac1a2f5b7555ea17a.jpg","type":"image","desc":"the sun is shining brightly in the dark sky over an empty space with no clouds","cat":"lofi"},{"url":"https://i.pinimg.com/originals/7a/65/e5/7a65e5332407c7c2ee0020d9ff951b70.jpg","type":"image","desc":"the cross is made up of white lines on a black background, and it appears to be very intricate","cat":"lofi"},{"url":"https://i.pinimg.com/originals/63/75/f7/6375f750e2019b6317502ebf692bb5d6.jpg","type":"image","desc":"an orange and yellow painting on a black background with red flowers in the foreground","cat":"lofi"},{"url":"https://i.pinimg.com/originals/21/63/1a/21631a0d11ccde22a560150af433f6e5.jpg","type":"image","desc":"black and white photograph of plastic bottle caps","cat":"lofi"},{"url":"https://i.pinimg.com/originals/c3/20/42/c320420f590fac16ee284c34c5c1cd4f.jpg","type":"image","desc":"a goldfish swimming in the blue water","cat":"lofi"},{"url":"https://i.pinimg.com/originals/6f/bd/d7/6fbdd79f645891ddae16211a90c2a639.jpg","type":"image","desc":"a person running across a field with a kite flying above","cat":"lofi"},{"url":"https://i.pinimg.com/originals/f5/63/6a/f5636a5bad3652bb925f64aae7236d45.jpg","type":"image","desc":"an old frame hanging on the wall with a red background and gold trim around it","cat":"lofi"},{"url":"https://i.pinimg.com/originals/21/24/b7/2124b77c9f0390e8625fb36e9066fb15.jpg","type":"image","desc":"an airplane flying through the air on top of a black background with blue writing and stars","cat":"lofi"},{"url":"https://i.pinimg.com/originals/c7/f6/eb/c7f6ebaa517aa8be84d03c8498674169.jpg","type":"image","desc":"three jellyfish swimming in the dark water at night with orange lights on their heads","cat":"lofi"},{"url":"https://i.pinimg.com/originals/48/15/3b/48153b89b06c7da417292a5cb6994db6.jpg","type":"image","desc":"three cats laying on top of each other in the air with their tails curled up","cat":"lofi"},{"url":"https://i.pinimg.com/originals/9f/96/af/9f96af8ba2b1708587747952e1dbf244.jpg","type":"image","desc":"a green and black floral pattern with leaves on it's side, as well as the background","cat":"lofi"},{"url":"https://i.pinimg.com/originals/b2/49/97/b2499779fb57314febf6a05a930f37b3.jpg","type":"image","desc":"a painting of a sunflower in the sky with clouds around it and a red heart at the center","cat":"lofi"},{"url":"https://i.pinimg.com/originals/fd/62/aa/fd62aaaf61e90de41558ebe03a6094e1.jpg","type":"image","desc":"an orange tree branch with fruit hanging from it's branches in front of a blue sky","cat":"lofi"},{"url":"https://i.pinimg.com/originals/b3/fa/76/b3fa763ecb749eb696a6057aec78687a.png","type":"image","desc":"a black background with gold stars on it","cat":"lofi"},{"url":"https://i.pinimg.com/originals/b5/61/c4/b561c4ca294b7397cf48828f872a9402.jpg","type":"image","desc":"a drawing of a person with their hands in the air","cat":"lofi"},{"url":"https://i.pinimg.com/originals/80/85/08/8085086ae1af1317cea8a97572402867.jpg","type":"image","desc":"a bunch of bugs and moths on a green background","cat":"lofi"},{"url":"https://i.pinimg.com/originals/5a/8e/06/5a8e06f664d51c8e64d025ffdd374c82.jpg","type":"image","desc":"the blue flowers are blooming on the stem","cat":"lofi"},{"url":"https://i.pinimg.com/originals/e6/8b/3a/e68b3a918466d4a349482d1ac44d5d2a.jpg","type":"image","desc":"an object in the dark sky with stars around it and a black hole behind it","cat":"lofi"},{"url":"https://i.pinimg.com/originals/e9/9b/a3/e99ba3e03786b2ee3d83284d8668c6f9.jpg","type":"image","desc":"a group of palm trees against an orange background","cat":"lofi"},{"url":"https://i.pinimg.com/originals/92/d3/10/92d310dc9ac1fc77a3b1fb1fe0e597db.jpg","type":"image","desc":"an old red book with gold trimming","cat":"lofi"},{"url":"https://i.pinimg.com/originals/9d/f6/de/9df6de49ae1cfb79d38d1c8ff0acc2d1.jpg","type":"image","desc":"a tree with green leaves and blue sky in the background","cat":"lofi"},{"url":"https://i.pinimg.com/originals/38/dd/5b/38dd5b63fbef0b9868adc48a89acb140.jpg","type":"image","desc":"a pile of playing cards sitting on top of a red table next to each other","cat":"lofi"},{"url":"https://i.pinimg.com/originals/4f/e5/df/4fe5df2c13d6a4e1b6a707388f29988e.jpg","type":"image","desc":"the sun is setting behind some power lines","cat":"lofi"},{"url":"https://i.pinimg.com/originals/50/d8/8f/50d88f28cae1ee50eead6d46335138b0.jpg","type":"image","desc":"white flowers are floating in the water on a green surface with metal bars behind them","cat":"lofi"},{"url":"https://i.pinimg.com/originals/0b/b2/e8/0bb2e89e5370e43579927706584aa715.jpg","type":"image","desc":"the earth logo on a blue background","cat":"lofi"},{"url":"https://i.pinimg.com/originals/a2/0b/1a/a20b1a0dee55262b4f73eb0feee261cb.jpg","type":"image","desc":"Functional Wallpaper, A53 Wallpaper, Boy Iphone Wallpaper, Wallpaper Samsung S22, Poster Wallpaper, Wallpaper Aesthetic Minimalist, Iphone 15 Wallpaper Aesthetic, Artsy Wallpaper, Minimalist Wallpaper Iphone Aesthetic","cat":"lofi"},{"url":"https://i.pinimg.com/originals/7e/1a/c7/7e1ac74eab2e75fddda5974938fc8643.jpg","type":"image","desc":"two blue dices on a black and white checkerboard pattern with one facing the camera","cat":"lofi"},{"url":"https://i.pinimg.com/originals/38/e4/54/38e45467aded27f69ffcd6bff9d3becf.jpg","type":"image","desc":"the sun is setting over the ocean with an orange and yellow sky in the background","cat":"lofi"},{"url":"https://i.pinimg.com/originals/20/6f/b5/206fb573d976f8aa495f7e69c0aa4bf0.jpg","type":"image","desc":"four different pictures of the same plane flying over water at night and sun setting in the distance","cat":"lofi"},{"url":"https://i.pinimg.com/originals/0c/34/c4/0c34c4b929e14f6b872a916f46b6cfee.jpg","type":"image","desc":"green palm trees against a blue sky","cat":"lofi"},{"url":"https://i.pinimg.com/originals/c5/38/f0/c538f0593591606d5242eadde56c12de.jpg","type":"image","desc":"an abstract pattern with flames in purple, yellow and pink","cat":"lofi"},{"url":"https://i.pinimg.com/originals/18/8a/5e/188a5ec1fe633ccab356ace543dfaf69.jpg","type":"image","desc":"red roses are on a black background, with leaves and flowers all over it's surface","cat":"lofi"},{"url":"https://i.pinimg.com/originals/06/83/6a/06836aab8131570a29a79d37088a7706.jpg","type":"image","desc":"an orange tree with lots of fruit growing on it's branches, against a blue sky","cat":"lofi"},{"url":"https://i.pinimg.com/originals/70/8c/43/708c43bd438ee989cf637f03a775bb30.png","type":"image","desc":"a red space ship flying through the night sky","cat":"lofi"},{"url":"https://i.pinimg.com/originals/50/b8/04/50b8048aa2961bdb7bf99b7555600224.jpg","type":"image","desc":"an abstract painting with black and orange colors on the bottom half of it, in front of a black background","cat":"lofi"},{"url":"https://i.pinimg.com/originals/b2/d6/dd/b2d6ddac51a3da23d7e2eb8deda32788.jpg","type":"image","desc":"a group of fish that are swimming in the water with orange and blue colors on them","cat":"lofi"},{"url":"https://i.pinimg.com/originals/3e/46/1a/3e461ab6f1e85a4ac8bd5759158cb5ae.jpg","type":"image","desc":"an image of a purple sky with some white papers flying in the air and one person on a skateboard","cat":"lofi"},{"url":"https://i.pinimg.com/originals/8b/cb/d7/8bcbd7388d9ea92af8bc1d026ea8cc93.jpg","type":"image","desc":"a black and white logo with an arrow pointing to the right, on a dark background","cat":"lofi"},{"url":"https://i.pinimg.com/originals/01/e5/91/01e591a2905a1aa8e6d555c902eaca7f.jpg","type":"image","desc":"an animal that is on the side of a blue wall with it's mouth open","cat":"lofi"},{"url":"https://i.pinimg.com/originals/26/b5/f0/26b5f0277986c49df966fc6cf29f1ec8.jpg","type":"image","desc":"an abstract green background with white swirls and circles on the top, in shades of yellow","cat":"lofi"},{"url":"https://i.pinimg.com/originals/20/22/2d/20222dd38f6a116953054cafe304ebcb.jpg","type":"image","desc":"an image of the face of a person with blue eyes and long eyelashes, in front of a blue background","cat":"lofi"},{"url":"https://i.pinimg.com/originals/71/08/43/7108432de37bd9dd236c649fdde576d3.png","type":"image","desc":"an abstract black and white background with swirls","cat":"lofi"},{"url":"https://i.pinimg.com/originals/b5/ac/57/b5ac5733eb5120f1748ac27a9736d4c2.jpg","type":"image","desc":"two tall palm trees against a red sky","cat":"lofi"},{"url":"https://i.pinimg.com/originals/c7/73/3d/c7733d613349d84c5a0c4af166697dcb.jpg","type":"image","desc":"two green and purple fabric with flowers on them","cat":"lofi"},{"url":"https://i.pinimg.com/originals/8a/8d/75/8a8d750e2b868ea5ea4fe596c9b4b5bb.jpg","type":"image","desc":"an insect is shown on the back of a black book with gold trimmings","cat":"lofi"},{"url":"https://i.pinimg.com/originals/3b/6c/4b/3b6c4b6c2f361fe902c3dca2993929c9.jpg","type":"image","desc":"an old book with some flowers on it","cat":"lofi"},{"url":"https://i.pinimg.com/originals/18/06/f3/1806f3c609aebbd6d1594d225bb359d5.jpg","type":"image","desc":"an intricately decorated rug with flowers and leaves","cat":"lofi"},{"url":"https://i.pinimg.com/originals/04/2c/55/042c5548c9e204f0cb11896154e79829.jpg","type":"image","desc":"an old book with flowers on it and a blue border around the cover that has gold trim","cat":"lofi"},{"url":"https://i.pinimg.com/originals/44/40/1d/44401d5174ae586dc0f361f465d34b43.jpg","type":"image","desc":"an old book with gold foil on the cover and green paper in the middle that says,","cat":"lofi"},{"url":"https://i.pinimg.com/originals/a0/02/49/a0024989a791b38ed10b24fcd96cf23c.png","type":"image","desc":"a single white flower on a red background","cat":"lofi"},{"url":"https://i.pinimg.com/originals/01/ad/99/01ad99e999faa0450362718146749b33.jpg","type":"image","desc":"two birds are flying in the sky with one bird on its back, and another bird above it","cat":"lofi"},{"url":"https://i.pinimg.com/originals/56/fb/fd/56fbfdf7545f6afc6ac3df722b889e8e.jpg","type":"image","desc":"Book Cover Design Inspiration, Wattpad Book Covers, Book Cover Template, Vintage Book Covers, Book Cover Art, Cover Template, Book Cover Design, Album Art, Vintage Book","cat":"lofi"},{"url":"https://i.pinimg.com/originals/4f/e5/91/4fe591b6c0ac7823f649be69a3711fb2.jpg","type":"image","desc":"an old book with a drawing of a deer's head on it","cat":"lofi"},{"url":"https://i.pinimg.com/originals/0e/d9/f4/0ed9f443640f656148e7ba8b54b59ce2.jpg","type":"image","desc":"a green book with gold flowers on it","cat":"lofi"},{"url":"https://i.pinimg.com/originals/45/e4/2c/45e42c8a579b6280916a3e5b8ed53be8.jpg","type":"image","desc":"a gold bird sitting on top of a blue book","cat":"lofi"},{"url":"https://i.pinimg.com/originals/b9/bb/60/b9bb60240eeec3ff0d897458247fae01.jpg","type":"image","desc":"the front cover of a book with an image of a boat and house in the background","cat":"lofi"},{"url":"https://i.pinimg.com/originals/08/5e/24/085e2408d7c0280abe144b39b6cee8c9.jpg","type":"image","desc":"an old book with gold and black designs on it","cat":"lofi"},{"url":"https://i.pinimg.com/originals/d4/84/4e/d4844ef40c94a75c4bd4e4524f62dece.jpg","type":"image","desc":"an old book with flowers on it","cat":"lofi"},{"url":"https://i.pinimg.com/originals/04/22/a7/0422a738f1c660034c7d50a6a9bd991e.png","type":"image","desc":"an old red book with gold trimming","cat":"lofi"},{"url":"https://i.pinimg.com/originals/78/1f/4d/781f4db93fe0d26b20b666c46308a39f.jpg","type":"image","desc":"an old book with flowers on the cover","cat":"lofi"},{"url":"https://i.pinimg.com/originals/e6/73/59/e67359472958fc18b173adaa7b93af65.jpg","type":"image","desc":"an old book with gold stars on it","cat":"lofi"},{"url":"https://i.pinimg.com/originals/31/06/d4/3106d46b6a0cd37da52cee5414fb6b1e.jpg","type":"image","desc":"a blue book with gold butterflies and flowers on the cover, in an ornate frame","cat":"lofi"},{"url":"https://i.pinimg.com/originals/a6/24/92/a624925e86b94485ab92384e050f13f1.jpg","type":"image","desc":"a green and gold book cover with flowers on it","cat":"lofi"},{"url":"https://i.pinimg.com/originals/cb/42/28/cb42281c1ab6bc68b1b23c323c6ae1bb.jpg","type":"image","desc":"a blue sky with a painting on it and a kite flying in the air above","cat":"lofi"},{"url":"https://i.pinimg.com/originals/14/a9/06/14a90659390e1c31b984c4c497b04976.jpg","type":"image","desc":"a painting of a city skyline at dusk","cat":"lofi"},{"url":"https://i.pinimg.com/originals/e4/f8/5e/e4f85e72cdb826b1d568b4a29756cd81.jpg","type":"image","desc":"an image of a tree with white flowers and blue squares in the bottom right corner","cat":"lofi"},{"url":"https://i.pinimg.com/originals/10/47/8b/10478b126cff29577f45c059125d1fac.jpg","type":"image","desc":"the sky is very dark and cloudy with some pink clouds in front of it,","cat":"lofi"},{"url":"https://i.pinimg.com/originals/23/d4/27/23d4279838232455bed1985e3ee6b9ad.jpg","type":"image","desc":"the sun is setting over some mountains and hills with buildings in the distance, as seen through a circular window","cat":"lofi"},{"url":"https://i.pinimg.com/originals/3d/a1/31/3da1311c8df3fbd7f6c95d4ea3e3b321.jpg","type":"image","desc":"a painting of a woman sitting at a table","cat":"lofi"},{"url":"https://i.pinimg.com/originals/42/7c/ea/427cea01b15d176cd18a8fde74aa4480.jpg","type":"image","desc":"a black star is flying in the sky","cat":"lofi"},{"url":"https://i.pinimg.com/originals/88/05/72/880572e9b3019fab7926d09ef1f811bd.jpg","type":"image","desc":"the sunset is reflected in the rear view mirror","cat":"lofi"},{"url":"https://i.pinimg.com/originals/1e/e3/27/1ee3279afee06d9dbbf5c741656c5396.png","type":"image","desc":"a black cat walking across a grass covered field","cat":"lofi"},{"url":"https://i.pinimg.com/originals/ff/59/0f/ff590fca79c69bd7a73f7617b08818b8.jpg","type":"image","desc":"an object flying in the sky over trees and hills on a clear day with blue skies","cat":"lofi"},{"url":"https://i.pinimg.com/originals/c4/f8/6b/c4f86b9ca046be58d05132fd417779a0.jpg","type":"image","desc":"two traffic lights hanging from wires in the sky at night with purple and blue hues","cat":"lofi"},{"url":"https://i.pinimg.com/originals/9d/40/05/9d4005a9ac5c483394b730dd1de48ede.jpg","type":"image","desc":"an image of a person floating in the water with mountains and clouds behind them at night","cat":"lofi"},{"url":"https://i.pinimg.com/originals/b7/c5/de/b7c5de8126c0ee808c8b32b6c80af9b3.jpg","type":"image","desc":"a person flying a kite in the sky with a rainbow colored cloud behind them and a man standing on top of a hill","cat":"lofi"},{"url":"https://i.pinimg.com/originals/93/be/58/93be583349317d6a5ed095c9dff907c5.jpg","type":"image","desc":"red roses are blooming in the garden","cat":"lofi"},{"url":"https://i.pinimg.com/originals/85/77/f8/8577f84d2c247a77726b5eba1a36e55c.jpg","type":"image","desc":"an image of the ocean with waves in blue and white ink on paper, as if it were drawn by hand or colored pencils","cat":"lofi"},{"url":"https://i.pinimg.com/originals/12/24/46/1224468f443bd10355346b62dfed0a99.jpg","type":"image","desc":"the flowers are blooming all over the place and it is hard to tell what color they are","cat":"lofi"},{"url":"https://i.pinimg.com/originals/3c/2e/6a/3c2e6ac3f0de672a6f3b16a646983877.jpg","type":"image","desc":"a pink flower with green leaves in front of a black background that has the colors of the rainbow on it","cat":"lofi"},{"url":"https://i.pinimg.com/originals/e4/f2/70/e4f270cc222c2f7f28238d09044f4550.jpg","type":"image","desc":"a painting of flowers in a vase on a table","cat":"lofi"},{"url":"https://i.pinimg.com/originals/9c/5f/3d/9c5f3d6f70b5054c96a598c47925fdb5.jpg","type":"image","desc":"a small white butterfly flying through the air","cat":"lofi"},{"url":"https://i.pinimg.com/originals/af/41/5a/af415a8464774d13477128891c5775d0.jpg","type":"image","desc":"an image of flowers in the dark with no one around them or on the ground","cat":"lofi"},{"url":"https://i.pinimg.com/originals/fa/56/c5/fa56c5dd7e33ba7a0fa5eaf5d6cbd915.jpg","type":"image","desc":"an airplane flying through the dark sky with its light shining on it's side","cat":"lofi"},{"url":"https://i.pinimg.com/originals/1b/31/cb/1b31cbe1623d4d6c8efeb03a6e380f9f.jpg","type":"image","desc":"three jellyfish swimming in the dark water","cat":"lofi"},{"url":"https://i.pinimg.com/originals/ad/6d/58/ad6d58426fb8b092a2ffdba37377a6f2.png","type":"image","desc":"water lilies are floating on the surface of a pond with green grass and red flowers","cat":"lofi"},{"url":"https://i.pinimg.com/originals/44/f9/b1/44f9b1e689bdf8478dd2b8181d3be968.jpg","type":"image","desc":"a single blue flower in the dark with its stem still on it's end","cat":"lofi"},{"url":"https://i.pinimg.com/originals/d3/95/9f/d3959f2b2e1c06bf6e82a9c0bb9c11f4.jpg","type":"image","desc":"the sky is filled with clouds and blue skies","cat":"lofi"},{"url":"https://i.pinimg.com/originals/8f/e8/33/8fe833418bffa0c96b00572da062e52d.jpg","type":"image","desc":"an abstract black and white photo with lines","cat":"lofi"},{"url":"https://i.pinimg.com/originals/fa/40/0b/fa400b80bcbb5e0b2e36a9758e9646d4.jpg","type":"image","desc":"a stack of books sitting on top of each other in front of a black background","cat":"lofi"},{"url":"https://i.pinimg.com/originals/fd/d5/88/fdd588f4b999b807374d474060612808.jpg","type":"image","desc":"two blue and white butterflies flying in the dark","cat":"lofi"},{"url":"https://i.pinimg.com/originals/23/2c/39/232c39af04243eb2238d423bfded67cc.jpg","type":"image","desc":"a pink rose is in the middle of a blue field with green leaves on it","cat":"lofi"},{"url":"https://i.pinimg.com/originals/57/98/e3/5798e318e0a721e6257e5bbf0686cb7f.jpg","type":"image","desc":"purple flowers are growing on the side of a building with a blue sky in the background","cat":"lofi"},{"url":"https://i.pinimg.com/originals/61/57/d3/6157d357ef79b7361e945149b82cfc76.jpg","type":"image","desc":"an airplane is flying in the sky over some water and buildings with people on it","cat":"lofi"},{"url":"https://i.pinimg.com/originals/6c/28/f2/6c28f272a41e4992fc5e2ec4dea8d14d.jpg","type":"image","desc":"a woman in a white dress and straw hat is standing on a hill with her back to the camera","cat":"lofi"},{"url":"https://i.pinimg.com/originals/8f/79/13/8f7913e93468dc36315b2a98814b0096.jpg","type":"image","desc":"two blue butterflies flying in the dark","cat":"lofi"},{"url":"https://i.pinimg.com/originals/aa/68/68/aa686823b8594ba824c8e3496b25d70e.jpg","type":"image","desc":"a laptop computer sitting on top of a table in the dark with hearts drawn on it","cat":"lofi"},{"url":"https://i.pinimg.com/originals/85/85/86/85858638c41fcd237065d7bd729d74f8.jpg","type":"image","desc":"the stars are in the shape of a crescent","cat":"lofi"},{"url":"https://i.pinimg.com/originals/e1/96/da/e196daf37e266c60c714584f2e47fbdb.jpg","type":"image","desc":"an image of two circles in the dark","cat":"lofi"},{"url":"https://i.pinimg.com/originals/38/b4/05/38b4057b22f2628a8d06c5783585d618.jpg","type":"image","desc":"an umbrella is lit up in the dark","cat":"lofi"},{"url":"https://i.pinimg.com/originals/be/fb/0a/befb0ab4e475390b6fef7eee559ff8a1.jpg","type":"image","desc":"the night sky with clouds and a full moon is seen through an opening in a window","cat":"lofi"},{"url":"https://i.pinimg.com/originals/27/c1/2c/27c12c5f41d5167f2f66e15e3ee20d1b.jpg","type":"image","desc":"an image of the solar system taken from space","cat":"lofi"},{"url":"https://i.pinimg.com/originals/d5/d1/c2/d5d1c2fe7948111d641f6b4930ab0feb.jpg","type":"image","desc":"a black background with purple flowers and the moon in the dark night sky above it","cat":"lofi"},{"url":"https://i.pinimg.com/originals/5b/04/e1/5b04e11c127fb31c2f0cb8317c326d7d.jpg","type":"image","desc":"a blue and white butterfly in the dark","cat":"lofi"},{"url":"https://i.pinimg.com/originals/2b/03/37/2b0337910e587e954f58b7e784ebc131.jpg","type":"image","desc":"A close-up illustration of a human eye with detailed eyelashes and eyebrow","cat":"lofi"}]